HStream/__init__.py
HStream/Server/HStreamApi_pb2.py
HStream/Server/HStreamApi_pb2_grpc.py
HStream/Server/__init__.py
hstreamdb_api-0.6.1.dist-info/METADATA
hstreamdb_api-0.6.1.dist-info/WHEEL
hstreamdb_api-0.6.1.dist-info/top_level.txt
hstreamdb_api-0.6.1.dist-info/RECORD
