Metadata-Version: 2.1
Name: hstreamdb-api
Version: 0.6.1
Summary: HStreamDB api for Python
Home-page: https://github.com/hstreamdb/hstream
Author: lambda
Author-email: lambda@emqx.io
License: UNKNOWN
Project-URL: Bug Tracker, https://github.com/hstreamdb/hstream/issues
Platform: UNKNOWN
Classifier: Programming Language :: Python :: 3
Classifier: License :: OSI Approved :: MIT License
Classifier: Operating System :: OS Independent
Requires-Python: >=3.7
Requires-Dist: protobuf
